pylibsass
sass
