Metadata-Version: 1.1
Name: pylibsass
Version: 0.1.4
Summary: Python wrapper for libsass
Home-page: http://github.com/rsenk330/pylibsass
Author: Ryan Senkbeil
Author-email: rsenk330@gmail.com
License: Copyright (c) 2013 Ryan Senkbeil
